{
  "comment": "OBSOLET/DEPRECATED: Bitte 'configs/braingraph_default_config.json' nutzen. Diese Datei bleibt nur zur Rückwärtskompatibilität.",
  "deprecated": true,
  "description": "Legacy sweep configuration. Prefer braingraph_default_config.json with sweep_parameters and sampling.",
  
  "dsi_studio_cmd": "/Applications/dsi_studio.app/Contents/MacOS/dsi_studio",
  
  "atlases": [
    "FreeSurferDKT_Cortical",
    "FreeSurferDKT_Tissue"
  ],
  
  "connectivity_values": [
    "count",
    "fa", 
    "qa",
    "ncount2"
  ],
  
  "tract_count": 50000,
  "thread_count": 6,
  
  "tracking_parameters": {
    "comment": "Default tracking parameters - will be overridden during sweep",
    "method": 0,
    "otsu_threshold": 0.6,
    "fa_threshold": 0.05,
    "turning_angle": 0.0,
    "step_size": 0.0,
    "smoothing": 0.0,
    "min_length": 10,
    "max_length": 200,
    "track_voxel_ratio": 2.0,
    "check_ending": 0,
    "random_seed": 0,
    "dt_threshold": 0.2
  },
  
  "connectivity_options": {
    "connectivity_type": "pass",
    "connectivity_threshold": 0.001,
    "connectivity_output": "matrix,connectogram,measure"
  },
  
  "sweep_parameters": {
    "comment": "Bitte primär braingraph_default_config.json verwenden. Hier grobe Default-Ranges (MATLAB-Notation erlaubt)",
    "description": "Coarse ranges for legacy sweeps",

    "otsu_range": "0.3:0.2:0.7",
    "fa_threshold_range": "0.05:0.05:0.20",
    "min_length_range": [10, 20, 30],
    "track_voxel_ratio_range": [2.0, 3.0, 4.0],
    "connectivity_threshold_range": [0.0005, 0.0010, 0.0020],
    "tract_count_range": [25000, 50000, 100000],

    "sampling": {
      "method": "grid",
      "n_samples": 24,
      "random_seed": 42
    },

    "sweep_tract_count": 50000,
    "quick_sweep": {
      "comment": "Kleine Ranges für schnellen Test",
      "otsu_range": "0.5:0.1:0.6",
      "fa_threshold_range": [0.10, 0.15],
      "min_length_range": [10, 20],
      "track_voxel_ratio_range": [2.0, 3.0],
      "connectivity_threshold_range": [0.0010, 0.0020],
      "tract_count_range": [25000, 50000],
      "sweep_tract_count": 25000
    }
  },
  
  "pipeline_integration": {
    "comment": "Settings for integration with the streamlined pipeline",
    "auto_run_analysis": false,
    "analysis_output_dir": "sweep_analysis",
    "generate_summary_plots": true
  },
  
  "quality_metrics": {
    "comment": "Target quality metrics for evaluation",
    "target_sparsity_range": [0.1, 0.4],
    "prefer_lower_sparsity": true,
    "minimum_connections": 100,
    "evaluate_small_worldness": true
  },
  
  "examples": {
    "basic_sweep": {
      "command": "./01_extract_connectome.sh --sweep --config sweep_config.json /data/subjects/ ./sweep_results/",
      "description": "Run full parameter sweep on all subjects"
    },
    
    "quick_test": {
      "command": "./01_extract_connectome.sh --quick-sweep --config sweep_config.json /data/pilot/ ./quick_test/", 
      "description": "Quick parameter validation on pilot data"
    },
    
    "with_analysis": {
      "commands": [
        "./01_extract_connectome.sh --sweep --config sweep_config.json /data/ ./sweep_results/",
        "python run_pipeline.py --input sweep_results/best_params/organized_matrices/ --output sweep_analysis/"
      ],
      "description": "Run sweep then analyze best parameters with full pipeline"
    }
  }
}
